broccoli_tool_creator/__init__.py
broccoli_tool_creator/api.py
broccoli_tool_creator/auth.py
broccoli_tool_creator/config.py
broccoli_tool_creator/service.py
broccoli_tool_creator-0.1.2.dist-info/licenses/LICENSE
broccoli_tool_creator-0.1.2.dist-info/METADATA
broccoli_tool_creator-0.1.2.dist-info/WHEEL
broccoli_tool_creator-0.1.2.dist-info/top_level.txt
broccoli_tool_creator-0.1.2.dist-info/RECORD
