Metadata-Version: 2.4
Name: broccoli-tool-creator
Version: 0.1.2
Summary: Automated tool creation for Broccoli Backend from FastAPI endpoints
Author-email: utkarsh-dailoqa <utkarsh.rastogi@dailoqa.com>
Classifier: Programming Language :: Python :: 3
Classifier: License :: OSI Approved :: MIT License
Classifier: Operating System :: OS Independent
Requires-Python: >=3.8
License-File: LICENSE
Requires-Dist: fastapi>=0.100.0
Requires-Dist: pydantic>=2.0.0
Requires-Dist: requests>=2.25.1
Requires-Dist: sqlalchemy>=2.0.0
Requires-Dist: httpx>=0.24.0
Dynamic: license-file
